README.md
setup.py
rio_tiler_mosaic/__init__.py
rio_tiler_mosaic/mosaic.py
rio_tiler_mosaic.egg-info/PKG-INFO
rio_tiler_mosaic.egg-info/SOURCES.txt
rio_tiler_mosaic.egg-info/dependency_links.txt
rio_tiler_mosaic.egg-info/not-zip-safe
rio_tiler_mosaic.egg-info/requires.txt
rio_tiler_mosaic.egg-info/top_level.txt
rio_tiler_mosaic/methods/__init__.py
rio_tiler_mosaic/methods/base.py
rio_tiler_mosaic/methods/defaults.py