Metadata-Version: 2.1
Name: rio-tiler-mosaic
Version: 0.0.1.dev5
Summary: A rio-tiler plugin to create mosaic tiles.
Home-page: https://github.com/cogeotiff/rio-tiler-mosaic
Author: Vincent Sarago
Author-email: vincent@developmentseed.org
License: MIT
Keywords: COG Mosaic GIS
Platform: UNKNOWN
Classifier: Intended Audience :: Information Technology
Classifier: Intended Audience :: Science/Research
Classifier: License :: OSI Approved :: BSD License
Classifier: Programming Language :: Python :: 3.6
Classifier: Topic :: Scientific/Engineering :: GIS
Requires-Python: >=3
Provides-Extra: test
Provides-Extra: dev
